WxwidgetsKuapingtaiGuiBiancheng/README.md
WxwidgetsKuapingtaiGuiBiancheng/__init__.py
WxwidgetsKuapingtaiGuiBiancheng/__main__.py
WxwidgetsKuapingtaiGuiBiancheng/file.epub
WxwidgetsKuapingtaiGuiBiancheng/index.html
WxwidgetsKuapingtaiGuiBiancheng/css/__init__.py
WxwidgetsKuapingtaiGuiBiancheng/css/annotations.css
WxwidgetsKuapingtaiGuiBiancheng/css/main.css
WxwidgetsKuapingtaiGuiBiancheng/css/normalize.css
WxwidgetsKuapingtaiGuiBiancheng/css/popup.css
WxwidgetsKuapingtaiGuiBiancheng/font/__init__.py
WxwidgetsKuapingtaiGuiBiancheng/font/fontello.eot
WxwidgetsKuapingtaiGuiBiancheng/font/fontello.svg
WxwidgetsKuapingtaiGuiBiancheng/font/fontello.ttf
WxwidgetsKuapingtaiGuiBiancheng/font/fontello.woff
WxwidgetsKuapingtaiGuiBiancheng/img/__init__.py
WxwidgetsKuapingtaiGuiBiancheng/img/annotator-glyph-sprite.png
WxwidgetsKuapingtaiGuiBiancheng/img/annotator-icon-sprite.png
WxwidgetsKuapingtaiGuiBiancheng/img/apple-touch-icon.png
WxwidgetsKuapingtaiGuiBiancheng/img/cancelfullscreen.png
WxwidgetsKuapingtaiGuiBiancheng/img/close.png
WxwidgetsKuapingtaiGuiBiancheng/img/fullscreen.png
WxwidgetsKuapingtaiGuiBiancheng/img/loader.gif
WxwidgetsKuapingtaiGuiBiancheng/img/menu-icon.png
WxwidgetsKuapingtaiGuiBiancheng/img/save.png
WxwidgetsKuapingtaiGuiBiancheng/img/saved.png
WxwidgetsKuapingtaiGuiBiancheng/img/settings-s.png
WxwidgetsKuapingtaiGuiBiancheng/img/settings.png
WxwidgetsKuapingtaiGuiBiancheng/img/star.png
WxwidgetsKuapingtaiGuiBiancheng/js/__init__.py
WxwidgetsKuapingtaiGuiBiancheng/js/epub.js
WxwidgetsKuapingtaiGuiBiancheng/js/epub.min.js
WxwidgetsKuapingtaiGuiBiancheng/js/epub.min.map
WxwidgetsKuapingtaiGuiBiancheng/js/hooks.min.js
WxwidgetsKuapingtaiGuiBiancheng/js/hooks.min.map
WxwidgetsKuapingtaiGuiBiancheng/js/reader.js
WxwidgetsKuapingtaiGuiBiancheng/js/reader.js.map
WxwidgetsKuapingtaiGuiBiancheng/js/reader.min.js
WxwidgetsKuapingtaiGuiBiancheng/js/reader.min.map
WxwidgetsKuapingtaiGuiBiancheng/js/hooks/__init__.py
wxwidgets_kuapingtai_gui_biancheng-2024.2.29.0.dist-info/METADATA
wxwidgets_kuapingtai_gui_biancheng-2024.2.29.0.dist-info/WHEEL
wxwidgets_kuapingtai_gui_biancheng-2024.2.29.0.dist-info/entry_points.txt
wxwidgets_kuapingtai_gui_biancheng-2024.2.29.0.dist-info/top_level.txt
wxwidgets_kuapingtai_gui_biancheng-2024.2.29.0.dist-info/RECORD
